LICENSE
README.md
setup.py
batch_sheet/CombinedSheet.py
batch_sheet/Sheet.py
batch_sheet/__init__.py
batch_sheet/admin.py
batch_sheet/apps.py
django_batch_sheet.egg-info/PKG-INFO
django_batch_sheet.egg-info/SOURCES.txt
django_batch_sheet.egg-info/dependency_links.txt
django_batch_sheet.egg-info/requires.txt
django_batch_sheet.egg-info/top_level.txt