Metadata-Version: 2.1
Name: django-batch-sheet
Version: 0.9.1
Summary: Create Excel Sheet from Django Model and load them automatically
Home-page: https://github.com/mkalioby/django-batch-sheet/
Author: Mohamed El-Kalioby, Mahmood Nasr
Author-email: mkalioby@mkalioby.com
License: MIT
Download-URL: https://github.com/mkalioby/django-batch-sheet/
Platform: UNKNOWN
Classifier: Development Status :: 5 - Production/Stable
Classifier: Environment :: Web Environment
Classifier: Framework :: Django
Classifier: Framework :: Django :: 2.2
Classifier: Framework :: Django :: 3.0
Classifier: Framework :: Django :: 3.1
Classifier: Framework :: Django :: 3.2
Classifier: Framework :: Django :: 4.0
Classifier: Framework :: Django :: 4.1
Classifier: Intended Audience :: Developers
Classifier: Operating System :: OS Independent
Classifier: Programming Language :: Python
Classifier: Programming Language :: Python :: 3
Classifier: Programming Language :: Python :: 3.7
Classifier: Programming Language :: Python :: 3.8
Classifier: Programming Language :: Python :: 3.9
Classifier: Programming Language :: Python :: 3.10
Classifier: Topic :: Software Development :: Libraries :: Python Modules
Requires-Python: >=3.5
License-File: LICENSE
